gradio_dropdownplus/__init__.py
gradio_dropdownplus/dropdownplus.py
gradio_dropdownplus/dropdownplus.pyi
gradio_dropdownplus/templates/component/Index-dsULWx_B.js
gradio_dropdownplus/templates/component/_basePickBy-LaQQ5Y1-.js
gradio_dropdownplus/templates/component/_baseUniq-DFIPcCrY.js
gradio_dropdownplus/templates/component/arc-Bt6Yqp6j.js
gradio_dropdownplus/templates/component/architectureDiagram-KFL7JDKH-wk_kwIXK.js
gradio_dropdownplus/templates/component/auto-render-BwaQGe8P.js
gradio_dropdownplus/templates/component/blockDiagram-ZYB65J3Q-DNWCWPbh.js
gradio_dropdownplus/templates/component/c4Diagram-AAMF2YG6-BeY_xb6D.js
gradio_dropdownplus/templates/component/channel-Ab7oN4Gk.js
gradio_dropdownplus/templates/component/chunk-ANTBXLJU-BwgTSljF.js
gradio_dropdownplus/templates/component/chunk-FHKO5MBM-CzrxxPWK.js
gradio_dropdownplus/templates/component/chunk-GLLZNHP4-DAmLcc0i.js
gradio_dropdownplus/templates/component/chunk-JBRWN2VN-19qyBxpW.js
gradio_dropdownplus/templates/component/chunk-LXBSTHXV-CNtjhS2l.js
gradio_dropdownplus/templates/component/chunk-NRVI72HA-CQ3LV39f.js
gradio_dropdownplus/templates/component/chunk-OMD6QJNC-DamKp1kC.js
gradio_dropdownplus/templates/component/chunk-WVR4S24B-Br22bM8P.js
gradio_dropdownplus/templates/component/classDiagram-3BZAVTQC-D45Rg7HK.js
gradio_dropdownplus/templates/component/classDiagram-v2-QTMF73CY-D45Rg7HK.js
gradio_dropdownplus/templates/component/clone-CHsVXWow.js
gradio_dropdownplus/templates/component/cytoscape.esm-ZmItrg9y.js
gradio_dropdownplus/templates/component/dagre-2BBEFEWP-C6CYCTFq.js
gradio_dropdownplus/templates/component/defaultLocale-D7EN2tov.js
gradio_dropdownplus/templates/component/diagram-4IRLE6MV-_4f03rOr.js
gradio_dropdownplus/templates/component/diagram-GUPCWM2R-C_OtVk8U.js
gradio_dropdownplus/templates/component/diagram-RP2FKANI-BH5Joxj1.js
gradio_dropdownplus/templates/component/erDiagram-HZWUO2LU-DULMf-mN.js
gradio_dropdownplus/templates/component/flowDiagram-THRYKUMA-C17Ahd-H.js
gradio_dropdownplus-0.0.3.dist-info/METADATA
gradio_dropdownplus-0.0.3.dist-info/WHEEL
gradio_dropdownplus-0.0.3.dist-info/RECORD
